cosent
