Metadata-Version: 1.1
Name: cosent.buildtools
Version: 1.1.3
Summary: Release scripts
Home-page: http://cosent.nl
Author: Guido Stevens
Author-email: guido.stevens@cosent.net
License: GPL
Keywords: python git buildout
Platform: UNKNOWN
Classifier: Development Status :: 4 - Beta
Classifier: Environment :: Console
Classifier: Intended Audience :: Developers
Classifier: License :: OSI Approved :: GNU General Public License (GPL)
Classifier: Operating System :: MacOS :: MacOS X
Classifier: Operating System :: POSIX
Classifier: Programming Language :: Python :: 2
